MANIFEST.in
data_flow_graph.py
setup.py
data_flow_graph.egg-info/PKG-INFO
data_flow_graph.egg-info/SOURCES.txt
data_flow_graph.egg-info/dependency_links.txt
data_flow_graph.egg-info/requires.txt
data_flow_graph.egg-info/top_level.txt